{
    "@class": "Animation",
    "id": {
        "uuid": "58BD1D2E-C1C7-4883-AF25-1C2097950911"
    },
    "tracks": [
        {
            "@class": "BoolBehaviorTrack",
            "clips": [
                {
                    "@class": "BoolBehaviorClip",
                    "beginTime": 0,
                    "duration": 0,
                    "script": "BoolValueBehaviorClipScript",
                    "behavior": {
                        "@class": "BoolDiscreteBehavior",
                        "frames": [
                            {
                                "@class": "BoolKeyFrame",
                                "formula": {
                                    "@class": "BoolExpressionFormula",
                                    "expression": "true"
                                },
                                "time": 0
                            }
                        ]
                    }
                }
            ],
            "script": "BoolBehaviorTrackScript",
            "accessor": "Object3DEnabledBlendAccessor"
        }
    ]
}