{
    "@class": "Collider",
    "id": {
        "uuid": "A22B2A1D-7234-4B2B-B38E-95FE1A3482D6"
    },
    "colliderInfo": [
        {
            "@class": "ColliderInfo",
            "collisionShape": "box",
            "alongAxis": "oy",
            "center": {
                "values": [
                    -8315.404296875,
                    1144.373779296875,
                    20.630416870117189
                ]
            },
            "params": {
                "values": [
                    518.27490234375,
                    41.5576171875,
                    357.0184326171875
                ]
            },
            "color": {
                "values": [
                    1.0,
                    1.0,
                    1.0
                ]
            },
            "isSelected": false
        }
    ]
}