{
    "@class": "Animation",
    "id": {
        "uuid": "CE29023A-9970-474C-AD9B-C19450B6B3AC"
    },
    "tracks": [
        {
            "@class": "BoolBehaviorTrack",
            "clips": [
                {
                    "@class": "BoolBehaviorClip",
                    "beginTime": 0,
                    "duration": 6600,
                    "script": "BoolValueBehaviorClipScript",
                    "behavior": {
                        "@class": "BoolDiscreteBehavior",
                        "frames": [
                            {
                                "@class": "BoolKeyFrame",
                                "formula": {
                                    "@class": "BoolExpressionFormula",
                                    "expression": "false"
                                },
                                "time": 6600
                            }
                        ]
                    }
                }
            ],
            "script": "BoolBehaviorTrackScript",
            "accessor": "ComponentPhysBodyEnabledAccessor"
        },
        {
            "@class": "StringBehaviorTrack",
            "clips": [
                {
                    "@class": "StringBehaviorClip",
                    "beginTime": 0,
                    "duration": 4300,
                    "script": "StringValueBehaviorClipScript",
                    "behavior": {
                        "@class": "StringDiscreteBehavior",
                        "frames": [
                            {
                                "@class": "StringKeyFrame",
                                "formula": {
                                    "@class": "StringExpressionFormula",
                                    "expression": "return ['rigidBody']"
                                },
                                "time": 4300
                            }
                        ]
                    }
                }
            ],
            "script": "StringBehaviorTrackScript",
            "accessor": "RigidBodyTypeAccessor"
        }
    ]
}