{"@class":"TimeLineScript","id":{"uuid":"6AAD61E7-2DC9-4A6A-A354-AE9FC6409743"},"name":"TimeLineScript","enableOnAwake":false,"loop":true,"jumpToFirstFrameAtEnd":false,"speed":1.0,"weight":1.0,"loopStartTime":0,"loopDuration":0,"is_imported":false,"type":"user","scripts":{"@class":"StdListRuntimeScript","list":[{"@class":"AnimationScript","id":{"uuid":"75C14503-DAFD-4CE6-9DF5-F7582DA09D2A"},"name":"AnimationScript","enableOnAwake":false,"OwnerLink":{"@class":"BindingLink","targetId":{"uuid":"0E721EA1-5763-4F2B-A100-7CF939287E44"}},"animation":{"uuid":"620BE45A-26CE-4516-8B2F-5C3718F63F84"},"AnimationType":"avar","is_imported":false,"isEnabled":true},{"@class":"AnimationScript","id":{"uuid":"83771605-F79A-441F-A076-36702C50549F"},"name":"AnimationScript","enableOnAwake":false,"OwnerLink":{"@class":"BindingLink","targetId":{"uuid":"1F45FFE8-BC1C-4699-8241-DE86D0ECCC3E"},"targetRelativeAddress":{"@class":"NodeRelativeAddressBase","index":46,"name":"Case 10"}},"animation":{"uuid":"4C2C7744-822E-4525-90C2-38764FC54B14"},"AnimationType":"object3D","is_imported":false,"isEnabled":true}]},"triggers":[{"@class":"AnimationTrigger","id":{"uuid":"434EABFA-1589-4EA2-89D1-B8985910EF65"},"ownerScriptId":{"uuid":"6AAD61E7-2DC9-4A6A-A354-AE9FC6409743"},"logicOperation":0,"resultType":0,"isInverted":false,"event":3,"bindingLink":{"@class":"BindingLink","targetId":{"uuid":"1ED0408F-15CC-439D-8536-C906D7FEFFD2"}}}],"symbolTable":{"@class":"VariousSymbolTable","id":{"uuid":"C88F7E28-3A2A-41AE-973D-BBB01DF24198"},"variables":[{"@class":"VariantVariable","id":{"uuid":"0E721EA1-5763-4F2B-A100-7CF939287E44"},"name":"s","type":"float","value":1.2799999713897706}]}}