{"@class":"TimeLineScript","id":{"uuid":"A5CADF2A-782A-4368-A433-228A8802999F"},"name":"TimeLineScript","enableOnAwake":false,"loop":true,"jumpToFirstFrameAtEnd":false,"speed":1.0,"weight":1.0,"loopStartTime":0,"loopDuration":0,"is_imported":false,"type":"user","scripts":{"@class":"StdListRuntimeScript","list":[{"@class":"AnimationScript","id":{"uuid":"A1DCF192-F652-4671-B228-441B67E95B3E"},"name":"AnimationScript","enableOnAwake":false,"OwnerLink":{"@class":"BindingLink","targetId":{"uuid":"89A02C38-2DC8-4FC4-B899-C14FF9D03CA5"}},"animation":{"uuid":"D3C11091-023A-4B5E-9073-7678FBE0DF69"},"AnimationType":"avar","is_imported":false,"isEnabled":true},{"@class":"AnimationScript","id":{"uuid":"65A31B43-4FB9-458E-B1CC-4B63A9921339"},"name":"AnimationScript","enableOnAwake":false,"OwnerLink":{"@class":"BindingLink","targetId":{"uuid":"18FB6310-B381-4DB4-AA55-4496F6A2D2B6"},"targetRelativeAddress":{"@class":"NodeRelativeAddressBase","index":1,"name":"Light"}},"animation":{"uuid":"CD446510-6FCB-49F0-8EEC-7A8FFCBE9787"},"AnimationType":"object3D","is_imported":false,"isEnabled":true},{"@class":"AnimationScript","id":{"uuid":"4D86F08C-D9B4-43AA-8E17-40B746BADC99"},"name":"AnimationScript","enableOnAwake":false,"OwnerLink":{"@class":"BindingLink","targetId":{"uuid":"F87FC679-9F4A-48F7-B17E-F0CC758C3FE7"}},"animation":{"uuid":"E4C5B963-815E-4816-A97D-3DFA2D4A4A16"},"AnimationType":"avar","is_imported":false,"isEnabled":true}]},"triggers":[{"@class":"AnimationTrigger","id":{"uuid":"9FE8C59B-8E77-42AA-80E2-FEE4413C2E15"},"ownerScriptId":{"uuid":"A5CADF2A-782A-4368-A433-228A8802999F"},"logicOperation":0,"resultType":0,"isInverted":false,"event":3,"bindingLink":{"@class":"BindingLink","targetId":{"uuid":"44013B97-B4C5-4828-976D-56E495B4D23F"}}}],"symbolTable":{"@class":"VariousSymbolTable","id":{"uuid":"CC2684D7-80BB-44D3-9FFC-D56A38C1F9DC"},"variables":[{"@class":"VariantVariable","id":{"uuid":"89A02C38-2DC8-4FC4-B899-C14FF9D03CA5"},"name":"s","type":"float","value":83.0},{"@class":"VariantVariable","id":{"uuid":"F87FC679-9F4A-48F7-B17E-F0CC758C3FE7"},"name":"sz","type":"float","value":96.0}]}}