{"@class":"TimeLineScript","id":{"uuid":"F796AE02-0302-439A-8ED3-C3349EDA3CDD"},"name":"Animations Animation 1","enableOnAwake":false,"duration":0,"loop":false,"jumpToFirstFrameAtEnd":false,"speed":1.0,"weight":1.0,"loopStartTime":0,"loopDuration":0,"is_imported":false,"type":"user","scripts":{"@class":"StdListRuntimeScript","list":[]},"triggers":[{"@class":"CollisionTrigger","id":{"uuid":"BE59A362-D82E-4F81-8CF9-6F6DCC02EE8B"},"ownerScriptId":{"uuid":"F796AE02-0302-439A-8ED3-C3349EDA3CDD"},"logicOperation":0,"resultType":0,"isInverted":false,"eventType":"out","targetBindingLink":{"@class":"BindingLink","targetId":{"uuid":"DFAD8647-0D8C-43FC-AAC9-971196A9A982"}},"zoneBindingLink":{"@class":"BindingLink","targetId":{"uuid":"8D555D50-AB6E-4F56-A1E1-D6763B567B4B"}},"allowed":false}],"animation_disabled_list":[]}