{"@class":"Material","id":{"uuid":"FAEBE6B6-2FD9-44F7-8A9E-CD5172850858"},"name":"M_Wall_01","renderingType":"opaque","blendingType":"normal","detailType":"none","lightningType":"perPixel","colorsType":"no","shadingType":"pbr","sideType":"front","depthType":"default","ambient":{"values":[0.48115652799606326,0.48115652799606326,0.48115652799606326]},"diffuse":{"values":[1.0,1.0,1.0]},"specular":{"values":[0.48115652799606326,0.48115652799606326,0.48115652799606326]},"emissive":{"values":[0.0,0.0,0.0]},"rimColor":{"values":[1.0,1.0,1.0]},"opacity":1.0,"shininess":20.0,"metalness":1.0,"roughness":1.0,"refraction":0.5,"rimIntensity":1.0,"bloomThreshold":1.0,"normalScale":1.0,"heightScale":1.0,"diffuseMap":{"uuid":"924577F5-E3E7-444A-BE09-11BD30C35963"},"normalMap":{"uuid":"CC98A1F6-AB6F-48A7-849B-1B2A129148C7"},"specularMap":{"uuid":"00000000-0000-0000-0000-000000000003"},"emissiveMap":{"uuid":"00000000-0000-0000-0000-000000000006"},"heightMap":{"uuid":"00000000-0000-0000-0000-000000000004"},"alphaMap":{"uuid":"00000000-0000-0000-0000-000000000001"},"occlusionMap":{"uuid":"7787B33E-F39D-4916-9811-A7A4D8B8B141"},"roughnessMap":{"uuid":"00000000-0000-0000-0000-000000000008"},"metalnessMap":{"uuid":"00000000-0000-0000-0000-000000000007"},"envMap":{"uuid":"00000000-0000-0000-0000-000000000009"},"irrEnvMap":{"uuid":"00000000-0000-0000-0000-000000000010"},"cubemapSize":256,"cubemapUpdateSpeed":-1,"tilingOffset":{"values":[1.0,1.0,0.0,0.0]},"toonGlare":{"values":[1.0,1.0,1.0]},"toonGradient":{"@class":"StdListVector3","list":[{"values":[0.25,0.25,0.25]},{"values":[0.6000000238418579,0.6000000238418579,0.6000000238418579]},{"values":[1.0,1.0,1.0]}]}}